{
  "manifest_version": 1,
  "id": "error_buzz",
  "name": "Error Buzz",
  "category": "ui",
  "description": "a short harsh buzz signalling an invalid or blocked action",
  "tags": [
    "error",
    "invalid",
    "denied",
    "buzz",
    "ui"
  ],
  "usage": "Invalid action, not enough money, blocked placement.",
  "loop": false,
  "engine": "procedural",
  "license": "CC0-1.0",
  "status": "complete",
  "file": "ui/error_buzz/error_buzz.wav",
  "format": "wav",
  "audio": {
    "samples": 6207,
    "duration_seconds": 0.141,
    "sample_rate": 44100,
    "channels": 1,
    "bit_depth": 16,
    "peak_normalized_to": 0.9
  },
  "procedural": {
    "family": "sfxr",
    "preset": "hitHurt",
    "seed": 3237547669,
    "params": {
      "wave_type": 1,
      "p_env_attack": 0.0,
      "p_env_sustain": 0.09937961446677014,
      "p_env_punch": 0.0,
      "p_env_decay": 0.22841246009165148,
      "p_base_freq": 0.7732173050274389,
      "p_freq_limit": 0.0,
      "p_freq_ramp": -0.4508799596375055,
      "p_freq_dramp": 0.0,
      "p_vib_strength": 0.0,
      "p_vib_speed": 0.0,
      "p_arp_mod": 0.0,
      "p_arp_speed": 0.0,
      "p_duty": 0.0,
      "p_duty_ramp": 0.0,
      "p_repeat_speed": 0.0,
      "p_pha_offset": 0.0,
      "p_pha_ramp": 0.0,
      "p_lpf_freq": 1.0,
      "p_lpf_ramp": 0.0,
      "p_lpf_resonance": 0.0,
      "p_hpf_freq": 0.0,
      "p_hpf_ramp": 0.0,
      "sound_vol": 0.5,
      "wave_type_name": "sawtooth"
    },
    "reproduce": "python pipeline/regen.py error_buzz"
  },
  "source": "procedural sfxr synth (pipeline/sfxr.py) \u2014 deterministic per (preset, seed)"
}