{
  "margins": {
    "tl": {
      "top": 40,
      "left": 43
    },
    "tr": {
      "top": 41,
      "right": 42
    },
    "bl": {
      "bottom": 44,
      "left": 44
    },
    "br": {
      "bottom": 44,
      "right": 44
    }
  },
  "art": {
    "w": 1408,
    "h": 768
  },
  "beams": {
    "top": {
      "y": 84,
      "h": 25
    },
    "bottom": {
      "y": 658,
      "h": 26
    },
    "left": {
      "x": 90,
      "w": 28
    },
    "right": {
      "x": 1290,
      "w": 28
    }
  },
  "corners": {
    "tl": {
      "w": 349,
      "h": 326
    },
    "tr": {
      "w": 350,
      "h": 326
    },
    "bl": {
      "w": 360,
      "h": 341
    },
    "br": {
      "w": 360,
      "h": 341
    }
  },
  "inner": {
    "top": 109,
    "bottom": 658,
    "left": 118,
    "right": 1290
  }
}