{
  "schema": "tiles2/sheet@1",
  "sheet": "base_x_2_1028431784",
  "ground_type": "black_mountain",
  "kind": "elevation",
  "height": "base_x_2",
  "levels": 2,
  "face_px": 32,
  "slot": 2,
  "objects": [
    "a black boulder",
    "a burnt fallen log",
    "a small steaming vent",
    "a pile of dark volcanic rocks",
    "a cooling lava rock with glowing cracks",
    "a cracked basalt slab",
    "a cluster of obsidian shards",
    "a chunk of black obsidian",
    "a black rock with a sulphur crust",
    "a small black crystal cluster"
  ],
  "tile_id": "23a4e1f1-ba3e-486d-a9c9-8b67e62119b7",
  "settings": {
    "endpoint": "/create-tiles-pro",
    "tile_type": "isometric",
    "tile_size": 64,
    "tile_view": "high top-down",
    "tile_view_angle": 28.0,
    "tile_depth_ratio": 0.0,
    "tile_height": 128,
    "tile_flat_top_px": 2,
    "levels": 2,
    "face_px": 32
  },
  "count": 16,
  "tiles": [
    {
      "index": 0,
      "file": "tile_00.png",
      "width": 64,
      "height": 128
    },
    {
      "index": 1,
      "file": "tile_01.png",
      "width": 64,
      "height": 128
    },
    {
      "index": 2,
      "file": "tile_02.png",
      "width": 64,
      "height": 128
    },
    {
      "index": 3,
      "file": "tile_03.png",
      "width": 64,
      "height": 128
    },
    {
      "index": 4,
      "file": "tile_04.png",
      "width": 64,
      "height": 128,
      "emission": {
        "material": "black_mountain",
        "color": [
          1.0,
          0.45,
          0.15
        ],
        "anim": "flicker",
        "sources": [
          {
            "x": 26.8,
            "y": 78.9,
            "r": 3.0,
            "color": [
              0.18,
              0.071,
              0.047
            ],
            "s": 0.338,
            "dir": "up"
          },
          {
            "x": 31.5,
            "y": 58.1,
            "r": 3.0,
            "color": [
              0.657,
              0.097,
              0.009
            ],
            "s": 0.439,
            "dir": "up"
          },
          {
            "x": 27.7,
            "y": 44.8,
            "r": 2.0,
            "color": [
              0.565,
              0.047,
              0.012
            ],
            "s": 0.37,
            "dir": "up"
          }
        ]
      },
      "features": [
        "shiny"
      ]
    },
    {
      "index": 5,
      "file": "tile_05.png",
      "width": 64,
      "height": 128,
      "emission": {
        "material": "black_mountain",
        "color": [
          1.0,
          0.45,
          0.15
        ],
        "anim": "flicker",
        "sources": [
          {
            "x": 31.7,
            "y": 63.6,
            "r": 2.3,
            "color": [
              0.39,
              0.057,
              0.02
            ],
            "s": 0.364,
            "dir": "up"
          },
          {
            "x": 18.8,
            "y": 75.0,
            "r": 2.0,
            "color": [
              0.571,
              0.092,
              0.04
            ],
            "s": 0.446,
            "dir": "up"
          },
          {
            "x": 47.2,
            "y": 74.3,
            "r": 2.0,
            "color": [
              0.484,
              0.042,
              0.037
            ],
            "s": 0.373,
            "dir": "up"
          }
        ]
      },
      "features": [
        "shiny"
      ]
    },
    {
      "index": 6,
      "file": "tile_06.png",
      "width": 64,
      "height": 128
    },
    {
      "index": 7,
      "file": "tile_07.png",
      "width": 64,
      "height": 128
    },
    {
      "index": 8,
      "file": "tile_08.png",
      "width": 64,
      "height": 128,
      "emission": {
        "material": "black_mountain",
        "color": [
          1.0,
          0.45,
          0.15
        ],
        "anim": "flicker",
        "sources": [
          {
            "x": 19.0,
            "y": 46.2,
            "r": 4.9,
            "color": [
              0.425,
              0.337,
              0.048
            ],
            "s": 0.584,
            "dir": "up"
          },
          {
            "x": 42.6,
            "y": 53.3,
            "r": 4.1,
            "color": [
              0.376,
              0.299,
              0.048
            ],
            "s": 0.551,
            "dir": "up"
          },
          {
            "x": 11.4,
            "y": 60.0,
            "r": 3.6,
            "color": [
              0.422,
              0.313,
              0.055
            ],
            "s": 0.571,
            "dir": "up"
          }
        ]
      },
      "features": [
        "shiny"
      ]
    },
    {
      "index": 9,
      "file": "tile_09.png",
      "width": 64,
      "height": 128
    },
    {
      "index": 10,
      "file": "tile_10.png",
      "width": 64,
      "height": 128
    },
    {
      "index": 11,
      "file": "tile_11.png",
      "width": 64,
      "height": 128
    },
    {
      "index": 12,
      "file": "tile_12.png",
      "width": 64,
      "height": 128,
      "emission": {
        "material": "black_mountain",
        "color": [
          1.0,
          0.45,
          0.15
        ],
        "anim": "flicker",
        "sources": [
          {
            "x": 31.5,
            "y": 57.0,
            "r": 2.0,
            "color": [
              0.692,
              0.094,
              0.028
            ],
            "s": 0.468,
            "dir": "up"
          }
        ]
      },
      "features": [
        "shiny"
      ]
    },
    {
      "index": 13,
      "file": "tile_13.png",
      "width": 64,
      "height": 128,
      "emission": {
        "material": "black_mountain",
        "color": [
          1.0,
          0.45,
          0.15
        ],
        "anim": "flicker",
        "sources": [
          {
            "x": 19.1,
            "y": 65.2,
            "r": 4.3,
            "color": [
              0.546,
              0.043,
              0.018
            ],
            "s": 0.375,
            "dir": "up"
          },
          {
            "x": 40.1,
            "y": 46.5,
            "r": 2.6,
            "color": [
              0.535,
              0.064,
              0.021
            ],
            "s": 0.4,
            "dir": "up"
          },
          {
            "x": 16.1,
            "y": 48.0,
            "r": 2.5,
            "color": [
              0.441,
              0.061,
              0.022
            ],
            "s": 0.379,
            "dir": "up"
          }
        ]
      },
      "features": [
        "shiny"
      ]
    },
    {
      "index": 14,
      "file": "tile_14.png",
      "width": 64,
      "height": 128
    },
    {
      "index": 15,
      "file": "tile_15.png",
      "width": 64,
      "height": 128
    }
  ],
  "emissive_tiles": 5,
  "generated_at": "2026-07-05T19:55:49+00:00",
  "processing": {
    "neutralize_outline": true,
    "harmonize": {
      "hue_strength": 0.9,
      "sat_strength": 0.7,
      "v_strength": 0.9,
      "hue_band": 65,
      "min_value": 14,
      "dark_material_value": 50,
      "dark_min_value": 38,
      "dark_include": 46
    },
    "harmonize_refs": [
      "black_mountain"
    ],
    "harmonized": 1,
    "fade_outline": {
      "enabled": true,
      "darkness_thresh": 60,
      "soft_lum": 120,
      "run_min": 9,
      "thick_max": 3,
      "strength": 0.6,
      "rim_strength": 0.4,
      "min_alpha": 0,
      "seam_strength": 0.4,
      "seam_jump": 70,
      "seam_bright": 130,
      "seam_nbr_sat": 90,
      "seam_rows": 1,
      "thin_lum_light": 120,
      "light_value": 180,
      "strength_light": 0.0,
      "rim_strength_light": 1.0,
      "soft_lum_light": 150,
      "protect_dark_material": true
    }
  }
}